py_jaws_namespace/__init__.py
py_jaws_namespace/decorators.py
py_jaws_namespace/namespace_registry.py
py_jaws_namespace/namespace_resolver.py
py_jaws_namespace-1.2.1.dist-info/METADATA
py_jaws_namespace-1.2.1.dist-info/WHEEL
py_jaws_namespace-1.2.1.dist-info/RECORD
